main.py
css/app.css
images/android-chrome-192x192.png
images/android-chrome-512x512.png
images/apple-touch-icon.png
images/favicon-16x16.png
images/favicon-32x32.png
images/favicon.ico
images/site.webmanifest
js/htmx.min.js
js/sse.js
kiezbox_messages-0.2.dist-info/LICENSE
kiezbox_messages-0.2.dist-info/METADATA
kiezbox_messages-0.2.dist-info/WHEEL
kiezbox_messages-0.2.dist-info/top_level.txt
kiezbox_messages-0.2.dist-info/RECORD
