Metadata-Version: 2.1
Name: kiezbox-messages
Version: 0.2
Summary: Kiezbox Messages App to send emergency calls
Project-URL: Homepage, https://github.com/technologiestiftung/kiezbox-messages
Project-URL: Issues, https://github.com/technologiestiftung/kiezbox-messages/issues
Project-URL: Project-Webpage, https://gemeinsamdigital.berlin.de/de/kiezbox-daten-in-alltag-und-krise/
Classifier: Programming Language :: Python :: 3
Classifier: License :: OSI Approved :: MIT License
Classifier: Operating System :: OS Independent
Requires-Python: >=3.11
License-File: LICENSE
Requires-Dist: fastapi <1
Requires-Dist: jinja2 <4
Requires-Dist: python-multipart <1
Requires-Dist: sse-starlette <3
Requires-Dist: sqlmodel <0.1
Requires-Dist: uvicorn[standard] <1
